odoo/addons/sale_partner_pricelist/README.rst
odoo/addons/sale_partner_pricelist/__init__.py
odoo/addons/sale_partner_pricelist/__manifest__.py
odoo/addons/sale_partner_pricelist/i18n/es.po
odoo/addons/sale_partner_pricelist/i18n/es_MX.po
odoo/addons/sale_partner_pricelist/i18n/it.po
odoo/addons/sale_partner_pricelist/i18n/sale_partner_pricelist.pot
odoo/addons/sale_partner_pricelist/models/__init__.py
odoo/addons/sale_partner_pricelist/models/res_company.py
odoo/addons/sale_partner_pricelist/models/res_config_settings.py
odoo/addons/sale_partner_pricelist/models/res_partner.py
odoo/addons/sale_partner_pricelist/models/sale_order.py
odoo/addons/sale_partner_pricelist/readme/CONFIGURE.rst
odoo/addons/sale_partner_pricelist/readme/CONTRIBUTORS.rst
odoo/addons/sale_partner_pricelist/readme/DESCRIPTION.rst
odoo/addons/sale_partner_pricelist/readme/USAGE.rst
odoo/addons/sale_partner_pricelist/static/description/icon.png
odoo/addons/sale_partner_pricelist/static/description/index.html
odoo/addons/sale_partner_pricelist/tests/__init__.py
odoo/addons/sale_partner_pricelist/tests/test_sale_pricelist.py
odoo/addons/sale_partner_pricelist/views/res_config_settings_view.xml
odoo/addons/sale_partner_pricelist/views/res_partner_view.xml
odoo/addons/sale_partner_pricelist/views/sale_order_view.xml
odoo_addon_sale_partner_pricelist-16.0.1.0.0.7.dist-info/METADATA
odoo_addon_sale_partner_pricelist-16.0.1.0.0.7.dist-info/WHEEL
odoo_addon_sale_partner_pricelist-16.0.1.0.0.7.dist-info/top_level.txt
odoo_addon_sale_partner_pricelist-16.0.1.0.0.7.dist-info/RECORD
